sha256/__init__.py
sha256/constants.py
sha256/sha256.py
sha256_brandonodiwuor-0.1.1.dist-info/LICENCE
sha256_brandonodiwuor-0.1.1.dist-info/METADATA
sha256_brandonodiwuor-0.1.1.dist-info/WHEEL
sha256_brandonodiwuor-0.1.1.dist-info/entry_points.txt
sha256_brandonodiwuor-0.1.1.dist-info/top_level.txt
sha256_brandonodiwuor-0.1.1.dist-info/RECORD
