Metadata-Version: 2.1
Name: sha256-brandonodiwuor
Version: 0.1.1
Summary: SHA256 Secure Hashing Algorithm(SHA) CLI app
Home-page: https://github.com/BrandonOdiwuor/sha256_project
Author: Brandon Odiwuor
Author-email: brandon.odiwuor@gmail.com
License: UNKNOWN
Project-URL: Bug Tracker, https://github.com/BrandonOdiwuor/sha256_project/issues
Platform: UNKNOWN
Classifier: Programming Language :: Python :: 3
Classifier: License :: OSI Approved :: MIT License
Classifier: Operating System :: OS Independent
Requires-Python: >=3.6
License-File: LICENCE
